GroupMkr/__init__.py
GroupMkr/shellster.py
GroupMkr-1.2.0.0.dist-info/LICENSE.txt
GroupMkr-1.2.0.0.dist-info/METADATA
GroupMkr-1.2.0.0.dist-info/WHEEL
GroupMkr-1.2.0.0.dist-info/top_level.txt
GroupMkr-1.2.0.0.dist-info/RECORD
