Metadata-Version: 2.1
Name: GroupMkr
Version: 1.2.0.0
Summary: GroupMkr is a module that simplifies creation of user groups and permissions in the terminal
Home-page: https://github.com/mezardini/GroupMkr.git
Download-URL: https://github.com/mezardini/GroupMkr/archive/refs/tags/1.0.0.1.tar.gz
Author: Olaoluwa Ajisola
Author-email: ajisolaolaoluwa@gmail.com
License: MIT
Keywords: Group,User Model,Django
Classifier: Development Status :: 3 - Alpha
Classifier: Intended Audience :: Developers
Classifier: Topic :: Software Development :: Build Tools
Classifier: License :: OSI Approved :: MIT License
Classifier: Programming Language :: Python :: 3
Classifier: Programming Language :: Python :: 3.4
Classifier: Programming Language :: Python :: 3.5
Classifier: Programming Language :: Python :: 3.6
License-File: LICENSE.txt
Requires-Dist: django
